smarty_left_pad/__init__.py
smarty_left_pad/__version__.py
smarty_left_pad/left_pad.py
smarty_left_pad-1.0.4.dist-info/LICENSE
smarty_left_pad-1.0.4.dist-info/LICENSE.txt
smarty_left_pad-1.0.4.dist-info/METADATA
smarty_left_pad-1.0.4.dist-info/WHEEL
smarty_left_pad-1.0.4.dist-info/top_level.txt
smarty_left_pad-1.0.4.dist-info/RECORD
