Metadata-Version: 2.1
Name: smarty-left-pad
Version: 1.0.4
Summary: Dynamic left pad creator
Home-page: https://github.com/nirmalchandra/smarty-left-pad
Author: Nirmal Chandra
Author-email: nirmal.fleet@gmail.com
License: Apache 2.0
Project-URL: Bug Reports, https://github.com/nirmalchandra/smarty-left-pad//issues
Project-URL: Source, https://github.com/nirmalchandra/smarty-left-pad/
Project-URL: Say Thanks!, https://github.com/nirmalchandra/smarty-left-pad
Project-URL: AboutMe, https://github.com/nirmalchandra
Keywords: leftpad left pad utility smarty-left-pad
Platform: UNKNOWN
Classifier: Development Status :: 3 - Alpha
Classifier: Intended Audience :: Developers
Classifier: Topic :: Software Development :: Build Tools
Classifier: Programming Language :: Python :: 3.8
Requires-Python: ~=3.8
